transformstorm/__init__.py
transformstorm/interfaces.py
transformstorm/textgenerator.py
transformstorm-0.1.8.data/scripts/transformstorm
transformstorm-0.1.8.dist-info/LICENSE
transformstorm-0.1.8.dist-info/METADATA
transformstorm-0.1.8.dist-info/WHEEL
transformstorm-0.1.8.dist-info/top_level.txt
transformstorm-0.1.8.dist-info/RECORD
