Metadata-Version: 2.1
Name: transformstorm
Version: 0.1.8
Summary: A command line interface for playing with language models
Home-page: https://github.com/simonmnash/transformstorm
Author: Simon Nash
Author-email: UNKNOWN
License: MIT
Platform: UNKNOWN
Requires-Dist: transformers
Requires-Dist: torch
Requires-Dist: click
